{
  "hash": "165986ba",
  "configHash": "28691988",
  "lockfileHash": "d478ad8c",
  "browserHash": "a3952c41",
  "optimized": {
    "react/jsx-dev-runtime": {
      "src": "../../node_modules/react/jsx-dev-runtime.js",
      "file": "react_jsx-dev-runtime.js",
      "fileHash": "10a7d232",
      "needsInterop": true
    },
    "react": {
      "src": "../../node_modules/react/index.js",
      "file": "react.js",
      "fileHash": "0a8ef10c",
      "needsInterop": true
    },
    "react-dom/client": {
      "src": "../../node_modules/react-dom/client.js",
      "file": "react-dom_client.js",
      "fileHash": "558dc646",
      "needsInterop": true
    },
    "zustand": {
      "src": "../../node_modules/zustand/esm/index.mjs",
      "file": "zustand.js",
      "fileHash": "cc9b9dbe",
      "needsInterop": false
    },
    "zustand/middleware": {
      "src": "../../node_modules/zustand/esm/middleware.mjs",
      "file": "zustand_middleware.js",
      "fileHash": "22f77f8d",
      "needsInterop": false
    },
    "html2canvas": {
      "src": "../../node_modules/html2canvas/dist/html2canvas.esm.js",
      "file": "html2canvas.js",
      "fileHash": "f54628c4",
      "needsInterop": false
    }
  },
  "chunks": {
    "chunk-WNPTCGAH": {
      "file": "chunk-WNPTCGAH.js"
    },
    "chunk-5WRI5ZAA": {
      "file": "chunk-5WRI5ZAA.js"
    }
  }
}